counter-16bit/counter_16bit.v
module counter_16bit (
    input clk,
    input rst_async,
    output reg [15:0] count
);
    // wire [15:0] count_last;
    // assign counter = 0;

    // reg [15:0] count;

    always @(posedge clk) 
        begin
            // active low reset
            if (rst_async) 
            begin
                count[15:0] <= count + 1'b1;                
            end
            else
                count <= 1'b0;
        end

    // assign counter[15:0] = count[15:0];


endmodule

counter-16bit/counter_16bit_tb.v
`timescale 1ns/1ns

module counter_16bit_tb (
    
);
    reg r_clk, r_rst_async;
    wire [15:0] w_count ;
    integer i;

    // instanciating DUT
    counter_16bit counter_1 (r_clk, r_rst_async, w_count[15:0]);

    initial begin
        r_clk = 1'b0;
        r_rst_async = 1'b0;
        #2;
        r_rst_async = 1'b1;
        w_count = 16'hfff0;
    end 
        
    // #10;

    // always begin
    //     r_clk = ~r_clk;
    //     #5;
    // end

    initial 
        begin
            $monitor(r_clk, w_count[15:0]);
            $dumpfile("counter_16bit.vcd");
            $dumpvars(0, counter_16bit_tb);

            // #2;
            for (i = 0; i < 1025 ; i = i + 1) begin

                r_clk <= ~r_clk;
                #1;
            end

            // r_rst_async = 1'b0;
            // for (i = 0; i < 4000 ; i = i + 1) begin

            //     r_clk <= ~r_clk;
            //     #1;
            // end
        
        end
endmodule

counter-16bit/counter_16bit.vcd
$date
	Sun Aug 15 15:56:51 2021
$end
$version
	Icarus Verilog
$end
$timescale
	1ns
$end
$scope module counter_16bit_tb $end
$var wire 16 ! w_count [15:0] $end
$var reg 1 " r_clk $end
$var reg 1 # r_rst_async $end
$var integer 32 $ i [31:0] $end
$scope module counter_1 $end
$var wire 1 " clk $end
$var wire 1 # rst_async $end
$var reg 16 % count [15:0] $end
$upscope $end
$upscope $end
$enddefinitions $end
#0
$dumpvars
b0 %
b0 $
0#
1"
b0 !
$end
#1
0"
b1 $
#2
b1 !
b1 %
1"
b10 $
1#
#3
0"
b11 $
#4
b10 !
b10 %
1"
b100 $
#5
0"
b101 $
#6
b11 !
b11 %
1"
b110 $
#7
0"
b111 $
#8
b100 !
b100 %
1"
b1000 $
#9
0"
b1001 $
#10
b101 !
b101 %
1"
b1010 $
#11
0"
b1011 $
#12
b110 !
b110 %
1"
b1100 $
#13
0"
b1101 $
#14
b111 !
b111 %
1"
b1110 $
#15
0"
b1111 $
#16
b1000 !
b1000 %
1"
b10000 $
#17
0"
b10001 $
#18
b1001 !
b1001 %
1"
b10010 $
#19
0"
b10011 $
#20
b1010 !
b1010 %
1"
b10100 $
#21
0"
b10101 $
#22
b1011 !
b1011 %
1"
b10110 $
#23
0"
b10111 $
#24
b1100 !
b1100 %
1"
b11000 $
#25
0"
b11001 $
#26
b1101 !
b1101 %
1"
b11010 $
#27
0"
b11011 $
#28
b1110 !
b1110 %
1"
b11100 $
#29
0"
b11101 $
#30
b1111 !
b1111 %
1"
b11110 $
#31
0"
b11111 $
#32
b10000 !
b10000 %
1"
b100000 $
#33
0"
b100001 $
#34
b10001 !
b10001 %
1"
b100010 $
#35
0"
b100011 $
#36
b10010 !
b10010 %
1"
b100100 $
#37
0"
b100101 $
#38
b10011 !
b10011 %
1"
b100110 $
#39
0"
b100111 $
#40
b10100 !
b10100 %
1"
b101000 $
#41
0"
b101001 $
#42
b10101 !
b10101 %
1"
b101010 $
#43
0"
b101011 $
#44
b10110 !
b10110 %
1"
b101100 $
#45
0"
b101101 $
#46
b10111 !
b10111 %
1"
b101110 $
#47
0"
b101111 $
#48
b11000 !
b11000 %
1"
b110000 $
#49
0"
b110001 $
#50
b11001 !
b11001 %
1"
b110010 $
#51
0"
b110011 $
#52
b11010 !
b11010 %
1"
b110100 $
#53
0"
b110101 $
#54
b11011 !
b11011 %
1"
b110110 $
#55
0"
b110111 $
#56
b11100 !
b11100 %
1"
b111000 $
#57
0"
b111001 $
#58
b11101 !
b11101 %
1"
b111010 $
#59
0"
b111011 $
#60
b11110 !
b11110 %
1"
b111100 $
#61
0"
b111101 $
#62
b11111 !
b11111 %
1"
b111110 $
#63
0"
b111111 $
#64
b100000 !
b100000 %
1"
b1000000 $
#65
0"
b1000001 $
#66
b100001 !
b100001 %
1"
b1000010 $
#67
0"
b1000011 $
#68
b100010 !
b100010 %
1"
b1000100 $
#69
0"
b1000101 $
#70
b100011 !
b100011 %
1"
b1000110 $
#71
0"
b1000111 $
#72
b100100 !
b100100 %
1"
b1001000 $
#73
0"
b1001001 $
#74
b100101 !
b100101 %
1"
b1001010 $
#75
0"
b1001011 $
#76
b100110 !
b100110 %
1"
b1001100 $
#77
0"
b1001101 $
#78
b100111 !
b100111 %
1"
b1001110 $
#79
0"
b1001111 $
#80
b101000 !
b101000 %
1"
b1010000 $
#81
0"
b1010001 $
#82
b101001 !
b101001 %
1"
b1010010 $
#83
0"
b1010011 $
#84
b101010 !
b101010 %
1"
b1010100 $
#85
0"
b1010101 $
#86
b101011 !
b101011 %
1"
b1010110 $
#87
0"
b1010111 $
#88
b101100 !
b101100 %
1"
b1011000 $
#89
0"
b1011001 $
#90
b101101 !
b101101 %
1"
b1011010 $
#91
0"
b1011011 $
#92
b101110 !
b101110 %
1"
b1011100 $
#93
0"
b1011101 $
#94
b101111 !
b101111 %
1"
b1011110 $
#95
0"
b1011111 $
#96
b110000 !
b110000 %
1"
b1100000 $
#97
0"
b1100001 $
#98
b110001 !
b110001 %
1"
b1100010 $
#99
0"
b1100011 $
#100
b110010 !
b110010 %
1"
b1100100 $
#101
0"
b1100101 $
#102
b110011 !
b110011 %
1"
b1100110 $
#103
0"
b1100111 $
#104
b110100 !
b110100 %
1"
b1101000 $
#105
0"
b1101001 $
#106
b110101 !
b110101 %
1"
b1101010 $
#107
0"
b1101011 $
#108
b110110 !
b110110 %
1"
b1101100 $
#109
0"
b1101101 $
#110
b110111 !
b110111 %
1"
b1101110 $
#111
0"
b1101111 $
#112
b111000 !
b111000 %
1"
b1110000 $
#113
0"
b1110001 $
#114
b111001 !
b111001 %
1"
b1110010 $
#115
0"
b1110011 $
#116
b111010 !
b111010 %
1"
b1110100 $
#117
0"
b1110101 $
#118
b111011 !
b111011 %
1"
b1110110 $
#119
0"
b1110111 $
#120
b111100 !
b111100 %
1"
b1111000 $
#121
0"
b1111001 $
#122
b111101 !
b111101 %
1"
b1111010 $
#123
0"
b1111011 $
#124
b111110 !
b111110 %
1"
b1111100 $
#125
0"
b1111101 $
#126
b111111 !
b111111 %
1"
b1111110 $
#127
0"
b1111111 $
#128
b1000000 !
b1000000 %
1"
b10000000 $
#129
0"
b10000001 $
#130
b1000001 !
b1000001 %
1"
b10000010 $
#131
0"
b10000011 $
#132
b1000010 !
b1000010 %
1"
b10000100 $
#133
0"
b10000101 $
#134
b1000011 !
b1000011 %
1"
b10000110 $
#135
0"
b10000111 $
#136
b1000100 !
b1000100 %
1"
b10001000 $
#137
0"
b10001001 $
#138
b1000101 !
b1000101 %
1"
b10001010 $
#139
0"
b10001011 $
#140
b1000110 !
b1000110 %
1"
b10001100 $
#141
0"
b10001101 $
#142
b1000111 !
b1000111 %
1"
b10001110 $
#143
0"
b10001111 $
#144
b1001000 !
b1001000 %
1"
b10010000 $
#145
0"
b10010001 $
#146
b1001001 !
b1001001 %
1"
b10010010 $
#147
0"
b10010011 $
#148
b1001010 !
b1001010 %
1"
b10010100 $
#149
0"
b10010101 $
#150
b1001011 !
b1001011 %
1"
b10010110 $
#151
0"
b10010111 $
#152
b1001100 !
b1001100 %
1"
b10011000 $
#153
0"
b10011001 $
#154
b1001101 !
b1001101 %
1"
b10011010 $
#155
0"
b10011011 $
#156
b1001110 !
b1001110 %
1"
b10011100 $
#157
0"
b10011101 $
#158
b1001111 !
b1001111 %
1"
b10011110 $
#159
0"
b10011111 $
#160
b1010000 !
b1010000 %
1"
b10100000 $
#161
0"
b10100001 $
#162
b1010001 !
b1010001 %
1"
b10100010 $
#163
0"
b10100011 $
#164
b1010010 !
b1010010 %
1"
b10100100 $
#165
0"
b10100101 $
#166
b1010011 !
b1010011 %
1"
b10100110 $
#167
0"
b10100111 $
#168
b1010100 !
b1010100 %
1"
b10101000 $
#169
0"
b10101001 $
#170
b1010101 !
b1010101 %
1"
b10101010 $
#171
0"
b10101011 $
#172
b1010110 !
b1010110 %
1"
b10101100 $
#173
0"
b10101101 $
#174
b1010111 !
b1010111 %
1"
b10101110 $
#175
0"
b10101111 $
#176
b1011000 !
b1011000 %
1"
b10110000 $
#177
0"
b10110001 $
#178
b1011001 !
b1011001 %
1"
b10110010 $
#179
0"
b10110011 $
#180
b1011010 !
b1011010 %
1"
b10110100 $
#181
0"
b10110101 $
#182
b1011011 !
b1011011 %
1"
b10110110 $
#183
0"
b10110111 $
#184
b1011100 !
b1011100 %
1"
b10111000 $
#185
0"
b10111001 $
#186
b1011101 !
b1011101 %
1"
b10111010 $
#187
0"
b10111011 $
#188
b1011110 !
b1011110 %
1"
b10111100 $
#189
0"
b10111101 $
#190
b1011111 !
b1011111 %
1"
b10111110 $
#191
0"
b10111111 $
#192
b1100000 !
b1100000 %
1"
b11000000 $
#193
0"
b11000001 $
#194
b1100001 !
b1100001 %
1"
b11000010 $
#195
0"
b11000011 $
#196
b1100010 !
b1100010 %
1"
b11000100 $
#197
0"
b11000101 $
#198
b1100011 !
b1100011 %
1"
b11000110 $
#199
0"
b11000111 $
#200
b1100100 !
b1100100 %
1"
b11001000 $
#201
0"
b11001001 $
#202
b1100101 !
b1100101 %
1"
b11001010 $
#203
0"
b11001011 $
#204
b1100110 !
b1100110 %
1"
b11001100 $
#205
0"
b11001101 $
#206
b1100111 !
b1100111 %
1"
b11001110 $
#207
0"
b11001111 $
#208
b1101000 !
b1101000 %
1"
b11010000 $
#209
0"
b11010001 $
#210
b1101001 !
b1101001 %
1"
b11010010 $
#211
0"
b11010011 $
#212
b1101010 !
b1101010 %
1"
b11010100 $
#213
0"
b11010101 $
#214
b1101011 !
b1101011 %
1"
b11010110 $
#215
0"
b11010111 $
#216
b1101100 !
b1101100 %
1"
b11011000 $
#217
0"
b11011001 $
#218
b1101101 !
b1101101 %
1"
b11011010 $
#219
0"
b11011011 $
#220
b1101110 !
b1101110 %
1"
b11011100 $
#221
0"
b11011101 $
#222
b1101111 !
b1101111 %
1"
b11011110 $
#223
0"
b11011111 $
#224
b1110000 !
b1110000 %
1"
b11100000 $
#225
0"
b11100001 $
#226
b1110001 !
b1110001 %
1"
b11100010 $
#227
0"
b11100011 $
#228
b1110010 !
b1110010 %
1"
b11100100 $
#229
0"
b11100101 $
#230
b1110011 !
b1110011 %
1"
b11100110 $
#231
0"
b11100111 $
#232
b1110100 !
b1110100 %
1"
b11101000 $
#233
0"
b11101001 $
#234
b1110101 !
b1110101 %
1"
b11101010 $
#235
0"
b11101011 $
#236
b1110110 !
b1110110 %
1"
b11101100 $
#237
0"
b11101101 $
#238
b1110111 !
b1110111 %
1"
b11101110 $
#239
0"
b11101111 $
#240
b1111000 !
b1111000 %
1"
b11110000 $
#241
0"
b11110001 $
#242
b1111001 !
b1111001 %
1"
b11110010 $
#243
0"
b11110011 $
#244
b1111010 !
b1111010 %
1"
b11110100 $
#245
0"
b11110101 $
#246
b1111011 !
b1111011 %
1"
b11110110 $
#247
0"
b11110111 $
#248
b1111100 !
b1111100 %
1"
b11111000 $
#249
0"
b11111001 $
#250
b1111101 !
b1111101 %
1"
b11111010 $
#251
0"
b11111011 $
#252
b1111110 !
b1111110 %
1"
b11111100 $
#253
0"
b11111101 $
#254
b1111111 !
b1111111 %
1"
b11111110 $
#255
0"
b11111111 $
#256
b10000000 !
b10000000 %
1"
b100000000 $
#257
0"
b100000001 $
#258
b10000001 !
b10000001 %
1"
b100000010 $
#259
0"
b100000011 $
#260
b10000010 !
b10000010 %
1"
b100000100 $
#261
0"
b100000101 $
#262
b10000011 !
b10000011 %
1"
b100000110 $
#263
0"
b100000111 $
#264
b10000100 !
b10000100 %
1"
b100001000 $
#265
0"
b100001001 $
#266
b10000101 !
b10000101 %
1"
b100001010 $
#267
0"
b100001011 $
#268
b10000110 !
b10000110 %
1"
b100001100 $
#269
0"
b100001101 $
#270
b10000111 !
b10000111 %
1"
b100001110 $
#271
0"
b100001111 $
#272
b10001000 !
b10001000 %
1"
b100010000 $
#273
0"
b100010001 $
#274
b10001001 !
b10001001 %
1"
b100010010 $
#275
0"
b100010011 $
#276
b10001010 !
b10001010 %
1"
b100010100 $
#277
0"
b100010101 $
#278
b10001011 !
b10001011 %
1"
b100010110 $
#279
0"
b100010111 $
#280
b10001100 !
b10001100 %
1"
b100011000 $
#281
0"
b100011001 $
#282
b10001101 !
b10001101 %
1"
b100011010 $
#283
0"
b100011011 $
#284
b10001110 !
b10001110 %
1"
b100011100 $
#285
0"
b100011101 $
#286
b10001111 !
b10001111 %
1"
b100011110 $
#287
0"
b100011111 $
#288
b10010000 !
b10010000 %
1"
b100100000 $
#289
0"
b100100001 $
#290
b10010001 !
b10010001 %
1"
b100100010 $
#291
0"
b100100011 $
#292
b10010010 !
b10010010 %
1"
b100100100 $
#293
0"
b100100101 $
#294
b10010011 !
b10010011 %
1"
b100100110 $
#295
0"
b100100111 $
#296
b10010100 !
b10010100 %
1"
b100101000 $
#297
0"
b100101001 $
#298
b10010101 !
b10010101 %
1"
b100101010 $
#299
0"
b100101011 $
#300
b10010110 !
b10010110 %
1"
b100101100 $
#301
0"
b100101101 $
#302
b10010111 !
b10010111 %
1"
b100101110 $
#303
0"
b100101111 $
#304
b10011000 !
b10011000 %
1"
b100110000 $
#305
0"
b100110001 $
#306
b10011001 !
b10011001 %
1"
b100110010 $
#307
0"
b100110011 $
#308
b10011010 !
b10011010 %
1"
b100110100 $
#309
0"
b100110101 $
#310
b10011011 !
b10011011 %
1"
b100110110 $
#311
0"
b100110111 $
#312
b10011100 !
b10011100 %
1"
b100111000 $
#313
0"
b100111001 $
#314
b10011101 !
b10011101 %
1"
b100111010 $
#315
0"
b100111011 $
#316
b10011110 !
b10011110 %
1"
b100111100 $
#317
0"
b100111101 $
#318
b10011111 !
b10011111 %
1"
b100111110 $
#319
0"
b100111111 $
#320
b10100000 !
b10100000 %
1"
b101000000 $
#321
0"
b101000001 $
#322
b10100001 !
b10100001 %
1"
b101000010 $
#323
0"
b101000011 $
#324
b10100010 !
b10100010 %
1"
b101000100 $
#325
0"
b101000101 $
#326
b10100011 !
b10100011 %
1"
b101000110 $
#327
0"
b101000111 $
#328
b10100100 !
b10100100 %
1"
b101001000 $
#329
0"
b101001001 $
#330
b10100101 !
b10100101 %
1"
b101001010 $
#331
0"
b101001011 $
#332
b10100110 !
b10100110 %
1"
b101001100 $
#333
0"
b101001101 $
#334
b10100111 !
b10100111 %
1"
b101001110 $
#335
0"
b101001111 $
#336
b10101000 !
b10101000 %
1"
b101010000 $
#337
0"
b101010001 $
#338
b10101001 !
b10101001 %
1"
b101010010 $
#339
0"
b101010011 $
#340
b10101010 !
b10101010 %
1"
b101010100 $
#341
0"
b101010101 $
#342
b10101011 !
b10101011 %
1"
b101010110 $
#343
0"
b101010111 $
#344
b10101100 !
b10101100 %
1"
b101011000 $
#345
0"
b101011001 $
#346
b10101101 !
b10101101 %
1"
b101011010 $
#347
0"
b101011011 $
#348
b10101110 !
b10101110 %
1"
b101011100 $
#349
0"
b101011101 $
#350
b10101111 !
b10101111 %
1"
b101011110 $
#351
0"
b101011111 $
#352
b10110000 !
b10110000 %
1"
b101100000 $
#353
0"
b101100001 $
#354
b10110001 !
b10110001 %
1"
b101100010 $
#355
0"
b101100011 $
#356
b10110010 !
b10110010 %
1"
b101100100 $
#357
0"
b101100101 $
#358
b10110011 !
b10110011 %
1"
b101100110 $
#359
0"
b101100111 $
#360
b10110100 !
b10110100 %
1"
b101101000 $
#361
0"
b101101001 $
#362
b10110101 !
b10110101 %
1"
b101101010 $
#363
0"
b101101011 $
#364
b10110110 !
b10110110 %
1"
b101101100 $
#365
0"
b101101101 $
#366
b10110111 !
b10110111 %
1"
b101101110 $
#367
0"
b101101111 $
#368
b10111000 !
b10111000 %
1"
b101110000 $
#369
0"
b101110001 $
#370
b10111001 !
b10111001 %
1"
b101110010 $
#371
0"
b101110011 $
#372
b10111010 !
b10111010 %
1"
b101110100 $
#373
0"
b101110101 $
#374
b10111011 !
b10111011 %
1"
b101110110 $
#375
0"
b101110111 $
#376
b10111100 !
b10111100 %
1"
b101111000 $
#377
0"
b101111001 $
#378
b10111101 !
b10111101 %
1"
b101111010 $
#379
0"
b101111011 $
#380
b10111110 !
b10111110 %
1"
b101111100 $
#381
0"
b101111101 $
#382
b10111111 !
b10111111 %
1"
b101111110 $
#383
0"
b101111111 $
#384
b11000000 !
b11000000 %
1"
b110000000 $
#385
0"
b110000001 $
#386
b11000001 !
b11000001 %
1"
b110000010 $
#387
0"
b110000011 $
#388
b11000010 !
b11000010 %
1"
b110000100 $
#389
0"
b110000101 $
#390
b11000011 !
b11000011 %
1"
b110000110 $
#391
0"
b110000111 $
#392
b11000100 !
b11000100 %
1"
b110001000 $
#393
0"
b110001001 $
#394
b11000101 !
b11000101 %
1"
b110001010 $
#395
0"
b110001011 $
#396
b11000110 !
b11000110 %
1"
b110001100 $
#397
0"
b110001101 $
#398
b11000111 !
b11000111 %
1"
b110001110 $
#399
0"
b110001111 $
#400
b11001000 !
b11001000 %
1"
b110010000 $
#401
0"
b110010001 $
#402
b11001001 !
b11001001 %
1"
b110010010 $
#403
0"
b110010011 $
#404
b11001010 !
b11001010 %
1"
b110010100 $
#405
0"
b110010101 $
#406
b11001011 !
b11001011 %
1"
b110010110 $
#407
0"
b110010111 $
#408
b11001100 !
b11001100 %
1"
b110011000 $
#409
0"
b110011001 $
#410
b11001101 !
b11001101 %
1"
b110011010 $
#411
0"
b110011011 $
#412
b11001110 !
b11001110 %
1"
b110011100 $
#413
0"
b110011101 $
#414
b11001111 !
b11001111 %
1"
b110011110 $
#415
0"
b110011111 $
#416
b11010000 !
b11010000 %
1"
b110100000 $
#417
0"
b110100001 $
#418
b11010001 !
b11010001 %
1"
b110100010 $
#419
0"
b110100011 $
#420
b11010010 !
b11010010 %
1"
b110100100 $
#421
0"
b110100101 $
#422
b11010011 !
b11010011 %
1"
b110100110 $
#423
0"
b110100111 $
#424
b11010100 !
b11010100 %
1"
b110101000 $
#425
0"
b110101001 $
#426
b11010101 !
b11010101 %
1"
b110101010 $
#427
0"
b110101011 $
#428
b11010110 !
b11010110 %
1"
b110101100 $
#429
0"
b110101101 $
#430
b11010111 !
b11010111 %
1"
b110101110 $
#431
0"
b110101111 $
#432
b11011000 !
b11011000 %
1"
b110110000 $
#433
0"
b110110001 $
#434
b11011001 !
b11011001 %
1"
b110110010 $
#435
0"
b110110011 $
#436
b11011010 !
b11011010 %
1"
b110110100 $
#437
0"
b110110101 $
#438
b11011011 !
b11011011 %
1"
b110110110 $
#439
0"
b110110111 $
#440
b11011100 !
b11011100 %
1"
b110111000 $
#441
0"
b110111001 $
#442
b11011101 !
b11011101 %
1"
b110111010 $
#443
0"
b110111011 $
#444
b11011110 !
b11011110 %
1"
b110111100 $
#445
0"
b110111101 $
#446
b11011111 !
b11011111 %
1"
b110111110 $
#447
0"
b110111111 $
#448
b11100000 !
b11100000 %
1"
b111000000 $
#449
0"
b111000001 $
#450
b11100001 !
b11100001 %
1"
b111000010 $
#451
0"
b111000011 $
#452
b11100010 !
b11100010 %
1"
b111000100 $
#453
0"
b111000101 $
#454
b11100011 !
b11100011 %
1"
b111000110 $
#455
0"
b111000111 $
#456
b11100100 !
b11100100 %
1"
b111001000 $
#457
0"
b111001001 $
#458
b11100101 !
b11100101 %
1"
b111001010 $
#459
0"
b111001011 $
#460
b11100110 !
b11100110 %
1"
b111001100 $
#461
0"
b111001101 $
#462
b11100111 !
b11100111 %
1"
b111001110 $
#463
0"
b111001111 $
#464
b11101000 !
b11101000 %
1"
b111010000 $
#465
0"
b111010001 $
#466
b11101001 !
b11101001 %
1"
b111010010 $
#467
0"
b111010011 $
#468
b11101010 !
b11101010 %
1"
b111010100 $
#469
0"
b111010101 $
#470
b11101011 !
b11101011 %
1"
b111010110 $
#471
0"
b111010111 $
#472
b11101100 !
b11101100 %
1"
b111011000 $
#473
0"
b111011001 $
#474
b11101101 !
b11101101 %
1"
b111011010 $
#475
0"
b111011011 $
#476
b11101110 !
b11101110 %
1"
b111011100 $
#477
0"
b111011101 $
#478
b11101111 !
b11101111 %
1"
b111011110 $
#479
0"
b111011111 $
#480
b11110000 !
b11110000 %
1"
b111100000 $
#481
0"
b111100001 $
#482
b11110001 !
b11110001 %
1"
b111100010 $
#483
0"
b111100011 $
#484
b11110010 !
b11110010 %
1"
b111100100 $
#485
0"
b111100101 $
#486
b11110011 !
b11110011 %
1"
b111100110 $
#487
0"
b111100111 $
#488
b11110100 !
b11110100 %
1"
b111101000 $
#489
0"
b111101001 $
#490
b11110101 !
b11110101 %
1"
b111101010 $
#491
0"
b111101011 $
#492
b11110110 !
b11110110 %
1"
b111101100 $
#493
0"
b111101101 $
#494
b11110111 !
b11110111 %
1"
b111101110 $
#495
0"
b111101111 $
#496
b11111000 !
b11111000 %
1"
b111110000 $
#497
0"
b111110001 $
#498
b11111001 !
b11111001 %
1"
b111110010 $
#499
0"
b111110011 $
#500
b11111010 !
b11111010 %
1"
b111110100 $
#501
0"
b111110101 $
#502
b11111011 !
b11111011 %
1"
b111110110 $
#503
0"
b111110111 $
#504
b11111100 !
b11111100 %
1"
b111111000 $
#505
0"
b111111001 $
#506
b11111101 !
b11111101 %
1"
b111111010 $
#507
0"
b111111011 $
#508
b11111110 !
b11111110 %
1"
b111111100 $
#509
0"
b111111101 $
#510
b11111111 !
b11111111 %
1"
b111111110 $
#511
0"
b111111111 $
#512
b100000000 !
b100000000 %
1"
b1000000000 $
#513
0"
b1000000001 $
#514
b100000001 !
b100000001 %
1"
b1000000010 $
#515
0"
b1000000011 $
#516
b100000010 !
b100000010 %
1"
b1000000100 $
#517
0"
b1000000101 $
#518
b100000011 !
b100000011 %
1"
b1000000110 $
#519
0"
b1000000111 $
#520
b100000100 !
b100000100 %
1"
b1000001000 $
#521
0"
b1000001001 $
#522
b100000101 !
b100000101 %
1"
b1000001010 $
#523
0"
b1000001011 $
#524
b100000110 !
b100000110 %
1"
b1000001100 $
#525
0"
b1000001101 $
#526
b100000111 !
b100000111 %
1"
b1000001110 $
#527
0"
b1000001111 $
#528
b100001000 !
b100001000 %
1"
b1000010000 $
#529
0"
b1000010001 $
#530
b100001001 !
b100001001 %
1"
b1000010010 $
#531
0"
b1000010011 $
#532
b100001010 !
b100001010 %
1"
b1000010100 $
#533
0"
b1000010101 $
#534
b100001011 !
b100001011 %
1"
b1000010110 $
#535
0"
b1000010111 $
#536
b100001100 !
b100001100 %
1"
b1000011000 $
#537
0"
b1000011001 $
#538
b100001101 !
b100001101 %
1"
b1000011010 $
#539
0"
b1000011011 $
#540
b100001110 !
b100001110 %
1"
b1000011100 $
#541
0"
b1000011101 $
#542
b100001111 !
b100001111 %
1"
b1000011110 $
#543
0"
b1000011111 $
#544
b100010000 !
b100010000 %
1"
b1000100000 $
#545
0"
b1000100001 $
#546
b100010001 !
b100010001 %
1"
b1000100010 $
#547
0"
b1000100011 $
#548
b100010010 !
b100010010 %
1"
b1000100100 $
#549
0"
b1000100101 $
#550
b100010011 !
b100010011 %
1"
b1000100110 $
#551
0"
b1000100111 $
#552
b100010100 !
b100010100 %
1"
b1000101000 $
#553
0"
b1000101001 $
#554
b100010101 !
b100010101 %
1"
b1000101010 $
#555
0"
b1000101011 $
#556
b100010110 !
b100010110 %
1"
b1000101100 $
#557
0"
b1000101101 $
#558
b100010111 !
b100010111 %
1"
b1000101110 $
#559
0"
b1000101111 $
#560
b100011000 !
b100011000 %
1"
b1000110000 $
#561
0"
b1000110001 $
#562
b100011001 !
b100011001 %
1"
b1000110010 $
#563
0"
b1000110011 $
#564
b100011010 !
b100011010 %
1"
b1000110100 $
#565
0"
b1000110101 $
#566
b100011011 !
b100011011 %
1"
b1000110110 $
#567
0"
b1000110111 $
#568
b100011100 !
b100011100 %
1"
b1000111000 $
#569
0"
b1000111001 $
#570
b100011101 !
b100011101 %
1"
b1000111010 $
#571
0"
b1000111011 $
#572
b100011110 !
b100011110 %
1"
b1000111100 $
#573
0"
b1000111101 $
#574
b100011111 !
b100011111 %
1"
b1000111110 $
#575
0"
b1000111111 $
#576
b100100000 !
b100100000 %
1"
b1001000000 $
#577
0"
b1001000001 $
#578
b100100001 !
b100100001 %
1"
b1001000010 $
#579
0"
b1001000011 $
#580
b100100010 !
b100100010 %
1"
b1001000100 $
#581
0"
b1001000101 $
#582
b100100011 !
b100100011 %
1"
b1001000110 $
#583
0"
b1001000111 $
#584
b100100100 !
b100100100 %
1"
b1001001000 $
#585
0"
b1001001001 $
#586
b100100101 !
b100100101 %
1"
b1001001010 $
#587
0"
b1001001011 $
#588
b100100110 !
b100100110 %
1"
b1001001100 $
#589
0"
b1001001101 $
#590
b100100111 !
b100100111 %
1"
b1001001110 $
#591
0"
b1001001111 $
#592
b100101000 !
b100101000 %
1"
b1001010000 $
#593
0"
b1001010001 $
#594
b100101001 !
b100101001 %
1"
b1001010010 $
#595
0"
b1001010011 $
#596
b100101010 !
b100101010 %
1"
b1001010100 $
#597
0"
b1001010101 $
#598
b100101011 !
b100101011 %
1"
b1001010110 $
#599
0"
b1001010111 $
#600
b100101100 !
b100101100 %
1"
b1001011000 $
#601
0"
b1001011001 $
#602
b100101101 !
b100101101 %
1"
b1001011010 $
#603
0"
b1001011011 $
#604
b100101110 !
b100101110 %
1"
b1001011100 $
#605
0"
b1001011101 $
#606
b100101111 !
b100101111 %
1"
b1001011110 $
#607
0"
b1001011111 $
#608
b100110000 !
b100110000 %
1"
b1001100000 $
#609
0"
b1001100001 $
#610
b100110001 !
b100110001 %
1"
b1001100010 $
#611
0"
b1001100011 $
#612
b100110010 !
b100110010 %
1"
b1001100100 $
#613
0"
b1001100101 $
#614
b100110011 !
b100110011 %
1"
b1001100110 $
#615
0"
b1001100111 $
#616
b100110100 !
b100110100 %
1"
b1001101000 $
#617
0"
b1001101001 $
#618
b100110101 !
b100110101 %
1"
b1001101010 $
#619
0"
b1001101011 $
#620
b100110110 !
b100110110 %
1"
b1001101100 $
#621
0"
b1001101101 $
#622
b100110111 !
b100110111 %
1"
b1001101110 $
#623
0"
b1001101111 $
#624
b100111000 !
b100111000 %
1"
b1001110000 $
#625
0"
b1001110001 $
#626
b100111001 !
b100111001 %
1"
b1001110010 $
#627
0"
b1001110011 $
#628
b100111010 !
b100111010 %
1"
b1001110100 $
#629
0"
b1001110101 $
#630
b100111011 !
b100111011 %
1"
b1001110110 $
#631
0"
b1001110111 $
#632
b100111100 !
b100111100 %
1"
b1001111000 $
#633
0"
b1001111001 $
#634
b100111101 !
b100111101 %
1"
b1001111010 $
#635
0"
b1001111011 $
#636
b100111110 !
b100111110 %
1"
b1001111100 $
#637
0"
b1001111101 $
#638
b100111111 !
b100111111 %
1"
b1001111110 $
#639
0"
b1001111111 $
#640
b101000000 !
b101000000 %
1"
b1010000000 $
#641
0"
b1010000001 $
#642
b101000001 !
b101000001 %
1"
b1010000010 $
#643
0"
b1010000011 $
#644
b101000010 !
b101000010 %
1"
b1010000100 $
#645
0"
b1010000101 $
#646
b101000011 !
b101000011 %
1"
b1010000110 $
#647
0"
b1010000111 $
#648
b101000100 !
b101000100 %
1"
b1010001000 $
#649
0"
b1010001001 $
#650
b101000101 !
b101000101 %
1"
b1010001010 $
#651
0"
b1010001011 $
#652
b101000110 !
b101000110 %
1"
b1010001100 $
#653
0"
b1010001101 $
#654
b101000111 !
b101000111 %
1"
b1010001110 $
#655
0"
b1010001111 $
#656
b101001000 !
b101001000 %
1"
b1010010000 $
#657
0"
b1010010001 $
#658
b101001001 !
b101001001 %
1"
b1010010010 $
#659
0"
b1010010011 $
#660
b101001010 !
b101001010 %
1"
b1010010100 $
#661
0"
b1010010101 $
#662
b101001011 !
b101001011 %
1"
b1010010110 $
#663
0"
b1010010111 $
#664
b101001100 !
b101001100 %
1"
b1010011000 $
#665
0"
b1010011001 $
#666
b101001101 !
b101001101 %
1"
b1010011010 $
#667
0"
b1010011011 $
#668
b101001110 !
b101001110 %
1"
b1010011100 $
#669
0"
b1010011101 $
#670
b101001111 !
b101001111 %
1"
b1010011110 $
#671
0"
b1010011111 $
#672
b101010000 !
b101010000 %
1"
b1010100000 $
#673
0"
b1010100001 $
#674
b101010001 !
b101010001 %
1"
b1010100010 $
#675
0"
b1010100011 $
#676
b101010010 !
b101010010 %
1"
b1010100100 $
#677
0"
b1010100101 $
#678
b101010011 !
b101010011 %
1"
b1010100110 $
#679
0"
b1010100111 $
#680
b101010100 !
b101010100 %
1"
b1010101000 $
#681
0"
b1010101001 $
#682
b101010101 !
b101010101 %
1"
b1010101010 $
#683
0"
b1010101011 $
#684
b101010110 !
b101010110 %
1"
b1010101100 $
#685
0"
b1010101101 $
#686
b101010111 !
b101010111 %
1"
b1010101110 $
#687
0"
b1010101111 $
#688
b101011000 !
b101011000 %
1"
b1010110000 $
#689
0"
b1010110001 $
#690
b101011001 !
b101011001 %
1"
b1010110010 $
#691
0"
b1010110011 $
#692
b101011010 !
b101011010 %
1"
b1010110100 $
#693
0"
b1010110101 $
#694
b101011011 !
b101011011 %
1"
b1010110110 $
#695
0"
b1010110111 $
#696
b101011100 !
b101011100 %
1"
b1010111000 $
#697
0"
b1010111001 $
#698
b101011101 !
b101011101 %
1"
b1010111010 $
#699
0"
b1010111011 $
#700
b101011110 !
b101011110 %
1"
b1010111100 $
#701
0"
b1010111101 $
#702
b101011111 !
b101011111 %
1"
b1010111110 $
#703
0"
b1010111111 $
#704
b101100000 !
b101100000 %
1"
b1011000000 $
#705
0"
b1011000001 $
