fullAdder/fullAdder.v
// this full adder is made directly, without calling 2 HAs

module fullAdder (
    input x0,
    input x1,
    input cin,
    output sum,
    output cout


);
    // what will happen during timing analysis??
    // assign sum = x0 ^ x1 ^ cin;     // single level logic
    assign {cout, sum} = x0 + x1 + cin;      // 2 level logic

endmodule

fullAdder/fullAdder_tb.v
module fullAdder_tb (
    
);
    reg r_BIT0 = 0;
    reg r_BIT1 = 0;
    reg r_CIN = 0;

    wire w_sum;
    wire w_cout;

    integer i;

    fullAdder FA_test(r_BIT0, r_BIT1, r_CIN, w_sum, w_cout);

    initial 
    begin

        $monitor(w_cout, w_sum);
        $dumpfile("fullAdder.vcd");
        $dumpvars(0, fullAdder_tb);

        for ( i = 0; i < 8 ; i = i+1) 
        begin

            // $display("current i value %d", i);
            {r_BIT0, r_BIT1, r_CIN}  = i;
            #5;
            
        end
        
    end

endmodule

fullAdder/fullAdder.vcd
$date
	Fri Jul 30 11:21:15 2021
$end
$version
	Icarus Verilog
$end
$timescale
	1s
$end
$scope module fullAdder_tb $end
$var wire 1 ! w_sum $end
$var wire 1 " w_cout $end
$var reg 1 # r_BIT0 $end
$var reg 1 $ r_BIT1 $end
$var reg 1 % r_CIN $end
$var integer 32 & i [31:0] $end
$scope module FA_test $end
$var wire 1 % cin $end
$var wire 1 # x0 $end
$var wire 1 $ x1 $end
$var wire 1 ! sum $end
$var wire 1 " cout $end
$upscope $end
$upscope $end
$enddefinitions $end
#0
$dumpvars
b0 &
0%
0$
0#
0"
0!
$end
#5
1!
1%
b1 &
#10
1$
0%
b10 &
#15
0!
1"
1%
b11 &
#20
1!
0"
1#
0$
0%
b100 &
#25
0!
1"
1%
b101 &
#30
1$
0%
b110 &
#35
1!
1%
b111 &
#40
b1000 &
